saplinkpackage/LicenseLock.pyd
saplinkpackage/SapAUTO.pyd
saplinkpackage/SapPLUGIN.pyd
saplinkpackage/SapREPORT.pyd
saplinkpackage/__init__.py
saplinkpackage-0.3.dist-info/METADATA
saplinkpackage-0.3.dist-info/WHEEL
saplinkpackage-0.3.dist-info/top_level.txt
saplinkpackage-0.3.dist-info/RECORD
